{
  "type": "File",
  "start": 0,
  "end": 758,
  "loc": {
    "start": {
      "line": 1,
      "column": 0
    },
    "end": {
      "line": 30,
      "column": 0
    }
  },
  "program": {
    "type": "Program",
    "start": 0,
    "end": 758,
    "loc": {
      "start": {
        "line": 1,
        "column": 0
      },
      "end": {
        "line": 30,
        "column": 0
      }
    },
    "sourceType": "module",
    "body": [
      {
        "type": "ExportDefaultDeclaration",
        "start": 248,
        "end": 757,
        "loc": {
          "start": {
            "line": 4,
            "column": 0
          },
          "end": {
            "line": 29,
            "column": 1
          }
        },
        "declaration": {
          "type": "ObjectExpression",
          "start": 263,
          "end": 757,
          "loc": {
            "start": {
              "line": 4,
              "column": 15
            },
            "end": {
              "line": 29,
              "column": 1
            }
          },
          "properties": [
            {
              "type": "ObjectProperty",
              "start": 314,
              "end": 355,
              "loc": {
                "start": {
                  "line": 8,
                  "column": 2
                },
                "end": {
                  "line": 8,
                  "column": 43
                }
              },
              "method": false,
              "shorthand": false,
              "computed": false,
              "key": {
                "type": "Identifier",
                "start": 314,
                "end": 332,
                "loc": {
                  "start": {
                    "line": 8,
                    "column": 2
                  },
                  "end": {
                    "line": 8,
                    "column": 20
                  },
                  "identifierName": "ElectronWARCWriter"
                },
                "name": "ElectronWARCWriter",
                "leadingComments": null
              },
              "value": {
                "type": "CallExpression",
                "start": 334,
                "end": 355,
                "loc": {
                  "start": {
                    "line": 8,
                    "column": 22
                  },
                  "end": {
                    "line": 8,
                    "column": 43
                  }
                },
                "callee": {
                  "type": "Identifier",
                  "start": 334,
                  "end": 341,
                  "loc": {
                    "start": {
                      "line": 8,
                      "column": 22
                    },
                    "end": {
                      "line": 8,
                      "column": 29
                    },
                    "identifierName": "require"
                  },
                  "name": "require"
                },
                "arguments": [
                  {
                    "type": "StringLiteral",
                    "start": 342,
                    "end": 354,
                    "loc": {
                      "start": {
                        "line": 8,
                        "column": 30
                      },
                      "end": {
                        "line": 8,
                        "column": 42
                      }
                    },
                    "extra": {
                      "rawValue": "./electron",
                      "raw": "'./electron'"
                    },
                    "value": "./electron"
                  }
                ]
              },
              "leadingComments": [
                {
                  "type": "CommentBlock",
                  "value": "*\n   * @type {ElectronWARCGenerator}\n   ",
                  "start": 267,
                  "end": 311,
                  "loc": {
                    "start": {
                      "line": 5,
                      "column": 2
                    },
                    "end": {
                      "line": 7,
                      "column": 5
                    }
                  }
                }
              ]
            },
            {
              "type": "ObjectProperty",
              "start": 411,
              "end": 460,
              "loc": {
                "start": {
                  "line": 13,
                  "column": 2
                },
                "end": {
                  "line": 13,
                  "column": 51
                }
              },
              "method": false,
              "shorthand": false,
              "computed": false,
              "key": {
                "type": "Identifier",
                "start": 411,
                "end": 433,
                "loc": {
                  "start": {
                    "line": 13,
                    "column": 2
                  },
                  "end": {
                    "line": 13,
                    "column": 24
                  },
                  "identifierName": "RemoteChromeWARCWriter"
                },
                "name": "RemoteChromeWARCWriter",
                "leadingComments": null
              },
              "value": {
                "type": "CallExpression",
                "start": 435,
                "end": 460,
                "loc": {
                  "start": {
                    "line": 13,
                    "column": 26
                  },
                  "end": {
                    "line": 13,
                    "column": 51
                  }
                },
                "callee": {
                  "type": "Identifier",
                  "start": 435,
                  "end": 442,
                  "loc": {
                    "start": {
                      "line": 13,
                      "column": 26
                    },
                    "end": {
                      "line": 13,
                      "column": 33
                    },
                    "identifierName": "require"
                  },
                  "name": "require"
                },
                "arguments": [
                  {
                    "type": "StringLiteral",
                    "start": 443,
                    "end": 459,
                    "loc": {
                      "start": {
                        "line": 13,
                        "column": 34
                      },
                      "end": {
                        "line": 13,
                        "column": 50
                      }
                    },
                    "extra": {
                      "rawValue": "./remoteChrome",
                      "raw": "'./remoteChrome'"
                    },
                    "value": "./remoteChrome"
                  }
                ]
              },
              "leadingComments": [
                {
                  "type": "CommentBlock",
                  "value": "*\n   * @type {RemoteChromeWARCGenerator}\n   ",
                  "start": 360,
                  "end": 408,
                  "loc": {
                    "start": {
                      "line": 10,
                      "column": 2
                    },
                    "end": {
                      "line": 12,
                      "column": 5
                    }
                  }
                }
              ]
            },
            {
              "type": "ObjectProperty",
              "start": 516,
              "end": 568,
              "loc": {
                "start": {
                  "line": 18,
                  "column": 2
                },
                "end": {
                  "line": 18,
                  "column": 54
                }
              },
              "method": false,
              "shorthand": false,
              "computed": false,
              "key": {
                "type": "Identifier",
                "start": 516,
                "end": 541,
                "loc": {
                  "start": {
                    "line": 18,
                    "column": 2
                  },
                  "end": {
                    "line": 18,
                    "column": 27
                  },
                  "identifierName": "PuppeteerCDPWARCGenerator"
                },
                "name": "PuppeteerCDPWARCGenerator",
                "leadingComments": null
              },
              "value": {
                "type": "CallExpression",
                "start": 543,
                "end": 568,
                "loc": {
                  "start": {
                    "line": 18,
                    "column": 29
                  },
                  "end": {
                    "line": 18,
                    "column": 54
                  }
                },
                "callee": {
                  "type": "Identifier",
                  "start": 543,
                  "end": 550,
                  "loc": {
                    "start": {
                      "line": 18,
                      "column": 29
                    },
                    "end": {
                      "line": 18,
                      "column": 36
                    },
                    "identifierName": "require"
                  },
                  "name": "require"
                },
                "arguments": [
                  {
                    "type": "StringLiteral",
                    "start": 551,
                    "end": 567,
                    "loc": {
                      "start": {
                        "line": 18,
                        "column": 37
                      },
                      "end": {
                        "line": 18,
                        "column": 53
                      }
                    },
                    "extra": {
                      "rawValue": "./puppeteerCDP",
                      "raw": "'./puppeteerCDP'"
                    },
                    "value": "./puppeteerCDP"
                  }
                ]
              },
              "leadingComments": [
                {
                  "type": "CommentBlock",
                  "value": "*\n   * @type {PuppeteerCDPWARCGenerator}\n   ",
                  "start": 465,
                  "end": 513,
                  "loc": {
                    "start": {
                      "line": 15,
                      "column": 2
                    },
                    "end": {
                      "line": 17,
                      "column": 5
                    }
                  }
                }
              ]
            },
            {
              "type": "ObjectProperty",
              "start": 621,
              "end": 667,
              "loc": {
                "start": {
                  "line": 23,
                  "column": 2
                },
                "end": {
                  "line": 23,
                  "column": 48
                }
              },
              "method": false,
              "shorthand": false,
              "computed": false,
              "key": {
                "type": "Identifier",
                "start": 621,
                "end": 643,
                "loc": {
                  "start": {
                    "line": 23,
                    "column": 2
                  },
                  "end": {
                    "line": 23,
                    "column": 24
                  },
                  "identifierName": "PuppeteerWARCGenerator"
                },
                "name": "PuppeteerWARCGenerator",
                "leadingComments": null
              },
              "value": {
                "type": "CallExpression",
                "start": 645,
                "end": 667,
                "loc": {
                  "start": {
                    "line": 23,
                    "column": 26
                  },
                  "end": {
                    "line": 23,
                    "column": 48
                  }
                },
                "callee": {
                  "type": "Identifier",
                  "start": 645,
                  "end": 652,
                  "loc": {
                    "start": {
                      "line": 23,
                      "column": 26
                    },
                    "end": {
                      "line": 23,
                      "column": 33
                    },
                    "identifierName": "require"
                  },
                  "name": "require"
                },
                "arguments": [
                  {
                    "type": "StringLiteral",
                    "start": 653,
                    "end": 666,
                    "loc": {
                      "start": {
                        "line": 23,
                        "column": 34
                      },
                      "end": {
                        "line": 23,
                        "column": 47
                      }
                    },
                    "extra": {
                      "rawValue": "./puppeteer",
                      "raw": "'./puppeteer'"
                    },
                    "value": "./puppeteer"
                  }
                ]
              },
              "leadingComments": [
                {
                  "type": "CommentBlock",
                  "value": "*\n   * @type {PuppeteerWARCGenerator}\n   ",
                  "start": 573,
                  "end": 618,
                  "loc": {
                    "start": {
                      "line": 20,
                      "column": 2
                    },
                    "end": {
                      "line": 22,
                      "column": 5
                    }
                  }
                }
              ]
            },
            {
              "type": "ObjectProperty",
              "start": 712,
              "end": 755,
              "loc": {
                "start": {
                  "line": 28,
                  "column": 2
                },
                "end": {
                  "line": 28,
                  "column": 45
                }
              },
              "method": false,
              "shorthand": false,
              "computed": false,
              "key": {
                "type": "Identifier",
                "start": 712,
                "end": 726,
                "loc": {
                  "start": {
                    "line": 28,
                    "column": 2
                  },
                  "end": {
                    "line": 28,
                    "column": 16
                  },
                  "identifierName": "WARCWriterBase"
                },
                "name": "WARCWriterBase",
                "leadingComments": null
              },
              "value": {
                "type": "CallExpression",
                "start": 728,
                "end": 755,
                "loc": {
                  "start": {
                    "line": 28,
                    "column": 18
                  },
                  "end": {
                    "line": 28,
                    "column": 45
                  }
                },
                "callee": {
                  "type": "Identifier",
                  "start": 728,
                  "end": 735,
                  "loc": {
                    "start": {
                      "line": 28,
                      "column": 18
                    },
                    "end": {
                      "line": 28,
                      "column": 25
                    },
                    "identifierName": "require"
                  },
                  "name": "require"
                },
                "arguments": [
                  {
                    "type": "StringLiteral",
                    "start": 736,
                    "end": 754,
                    "loc": {
                      "start": {
                        "line": 28,
                        "column": 26
                      },
                      "end": {
                        "line": 28,
                        "column": 44
                      }
                    },
                    "extra": {
                      "rawValue": "./warcWriterBase",
                      "raw": "'./warcWriterBase'"
                    },
                    "value": "./warcWriterBase"
                  }
                ]
              },
              "leadingComments": [
                {
                  "type": "CommentBlock",
                  "value": "*\n   * @type {WARCWriterBase}\n   ",
                  "start": 672,
                  "end": 709,
                  "loc": {
                    "start": {
                      "line": 25,
                      "column": 2
                    },
                    "end": {
                      "line": 27,
                      "column": 5
                    }
                  }
                }
              ]
            }
          ],
          "leadingComments": [
            {
              "type": "CommentBlock",
              "value": "*\n * @type {{ElectronWARCWriter: ElectronWARCGenerator, RemoteChromeWARCWriter: RemoteChromeWARCGenerator, PuppeteerCDPWARCGenerator: PuppeteerCDPWARCGenerator, PuppeteerWARCGenerator: PuppeteerWARCGenerator, WARCWriterBase: WARCWriterBase}}\n ",
              "start": 0,
              "end": 247,
              "loc": {
                "start": {
                  "line": 1,
                  "column": 0
                },
                "end": {
                  "line": 3,
                  "column": 3
                }
              }
            }
          ],
          "trailingComments": []
        },
        "leadingComments": [
          {
            "type": "CommentBlock",
            "value": "*\n * @type {{ElectronWARCWriter: ElectronWARCGenerator, RemoteChromeWARCWriter: RemoteChromeWARCGenerator, PuppeteerCDPWARCGenerator: PuppeteerCDPWARCGenerator, PuppeteerWARCGenerator: PuppeteerWARCGenerator, WARCWriterBase: WARCWriterBase}}\n ",
            "start": 0,
            "end": 247,
            "loc": {
              "start": {
                "line": 1,
                "column": 0
              },
              "end": {
                "line": 3,
                "column": 3
              }
            }
          }
        ]
      }
    ],
    "directives": []
  },
  "comments": [
    {
      "type": "CommentBlock",
      "value": "*\n * @type {{ElectronWARCWriter: ElectronWARCGenerator, RemoteChromeWARCWriter: RemoteChromeWARCGenerator, PuppeteerCDPWARCGenerator: PuppeteerCDPWARCGenerator, PuppeteerWARCGenerator: PuppeteerWARCGenerator, WARCWriterBase: WARCWriterBase}}\n ",
      "start": 0,
      "end": 247,
      "loc": {
        "start": {
          "line": 1,
          "column": 0
        },
        "end": {
          "line": 3,
          "column": 3
        }
      }
    },
    {
      "type": "CommentBlock",
      "value": "*\n   * @type {ElectronWARCGenerator}\n   ",
      "start": 267,
      "end": 311,
      "loc": {
        "start": {
          "line": 5,
          "column": 2
        },
        "end": {
          "line": 7,
          "column": 5
        }
      }
    },
    {
      "type": "CommentBlock",
      "value": "*\n   * @type {RemoteChromeWARCGenerator}\n   ",
      "start": 360,
      "end": 408,
      "loc": {
        "start": {
          "line": 10,
          "column": 2
        },
        "end": {
          "line": 12,
          "column": 5
        }
      }
    },
    {
      "type": "CommentBlock",
      "value": "*\n   * @type {PuppeteerCDPWARCGenerator}\n   ",
      "start": 465,
      "end": 513,
      "loc": {
        "start": {
          "line": 15,
          "column": 2
        },
        "end": {
          "line": 17,
          "column": 5
        }
      }
    },
    {
      "type": "CommentBlock",
      "value": "*\n   * @type {PuppeteerWARCGenerator}\n   ",
      "start": 573,
      "end": 618,
      "loc": {
        "start": {
          "line": 20,
          "column": 2
        },
        "end": {
          "line": 22,
          "column": 5
        }
      }
    },
    {
      "type": "CommentBlock",
      "value": "*\n   * @type {WARCWriterBase}\n   ",
      "start": 672,
      "end": 709,
      "loc": {
        "start": {
          "line": 25,
          "column": 2
        },
        "end": {
          "line": 27,
          "column": 5
        }
      }
    }
  ],
  "tokens": [
    {
      "type": "CommentBlock",
      "value": "*\n * @type {{ElectronWARCWriter: ElectronWARCGenerator, RemoteChromeWARCWriter: RemoteChromeWARCGenerator, PuppeteerCDPWARCGenerator: PuppeteerCDPWARCGenerator, PuppeteerWARCGenerator: PuppeteerWARCGenerator, WARCWriterBase: WARCWriterBase}}\n ",
      "start": 0,
      "end": 247,
      "loc": {
        "start": {
          "line": 1,
          "column": 0
        },
        "end": {
          "line": 3,
          "column": 3
        }
      }
    },
    {
      "type": {
        "label": "export",
        "keyword": "export",
        "beforeExpr": false,
        "startsExpr": false,
        "rightAssociative": false,
        "isLoop": false,
        "isAssign": false,
        "prefix": false,
        "postfix": false,
        "binop": null,
        "updateContext": null
      },
      "value": "export",
      "start": 248,
      "end": 254,
      "loc": {
        "start": {
          "line": 4,
          "column": 0
        },
        "end": {
          "line": 4,
          "column": 6
        }
      }
    },
    {
      "type": {
        "label": "default",
        "keyword": "default",
        "beforeExpr": true,
        "startsExpr": false,
        "rightAssociative": false,
        "isLoop": false,
        "isAssign": false,
        "prefix": false,
        "postfix": false,
        "binop": null,
        "updateContext": null
      },
      "value": "default",
      "start": 255,
      "end": 262,
      "loc": {
        "start": {
          "line": 4,
          "column": 7
        },
        "end": {
          "line": 4,
          "column": 14
        }
      }
    },
    {
      "type": {
        "label": "{",
        "beforeExpr": true,
        "startsExpr": true,
        "rightAssociative": false,
        "isLoop": false,
        "isAssign": false,
        "prefix": false,
        "postfix": false,
        "binop": null
      },
      "start": 263,
      "end": 264,
      "loc": {
        "start": {
          "line": 4,
          "column": 15
        },
        "end": {
          "line": 4,
          "column": 16
        }
      }
    },
    {
      "type": "CommentBlock",
      "value": "*\n   * @type {ElectronWARCGenerator}\n   ",
      "start": 267,
      "end": 311,
      "loc": {
        "start": {
          "line": 5,
          "column": 2
        },
        "end": {
          "line": 7,
          "column": 5
        }
      }
    },
    {
      "type": {
        "label": "name",
        "beforeExpr": false,
        "startsExpr": true,
        "rightAssociative": false,
        "isLoop": false,
        "isAssign": false,
        "prefix": false,
        "postfix": false,
        "binop": null
      },
      "value": "ElectronWARCWriter",
      "start": 314,
      "end": 332,
      "loc": {
        "start": {
          "line": 8,
          "column": 2
        },
        "end": {
          "line": 8,
          "column": 20
        }
      }
    },
    {
      "type": {
        "label": ":",
        "beforeExpr": true,
        "startsExpr": false,
        "rightAssociative": false,
        "isLoop": false,
        "isAssign": false,
        "prefix": false,
        "postfix": false,
        "binop": null,
        "updateContext": null
      },
      "start": 332,
      "end": 333,
      "loc": {
        "start": {
          "line": 8,
          "column": 20
        },
        "end": {
          "line": 8,
          "column": 21
        }
      }
    },
    {
      "type": {
        "label": "name",
        "beforeExpr": false,
        "startsExpr": true,
        "rightAssociative": false,
        "isLoop": false,
        "isAssign": false,
        "prefix": false,
        "postfix": false,
        "binop": null
      },
      "value": "require",
      "start": 334,
      "end": 341,
      "loc": {
        "start": {
          "line": 8,
          "column": 22
        },
        "end": {
          "line": 8,
          "column": 29
        }
      }
    },
    {
      "type": {
        "label": "(",
        "beforeExpr": true,
        "startsExpr": true,
        "rightAssociative": false,
        "isLoop": false,
        "isAssign": false,
        "prefix": false,
        "postfix": false,
        "binop": null
      },
      "start": 341,
      "end": 342,
      "loc": {
        "start": {
          "line": 8,
          "column": 29
        },
        "end": {
          "line": 8,
          "column": 30
        }
      }
    },
    {
      "type": {
        "label": "string",
        "beforeExpr": false,
        "startsExpr": true,
        "rightAssociative": false,
        "isLoop": false,
        "isAssign": false,
        "prefix": false,
        "postfix": false,
        "binop": null,
        "updateContext": null
      },
      "value": "./electron",
      "start": 342,
      "end": 354,
      "loc": {
        "start": {
          "line": 8,
          "column": 30
        },
        "end": {
          "line": 8,
          "column": 42
        }
      }
    },
    {
      "type": {
        "label": ")",
        "beforeExpr": false,
        "startsExpr": false,
        "rightAssociative": false,
        "isLoop": false,
        "isAssign": false,
        "prefix": false,
        "postfix": false,
        "binop": null
      },
      "start": 354,
      "end": 355,
      "loc": {
        "start": {
          "line": 8,
          "column": 42
        },
        "end": {
          "line": 8,
          "column": 43
        }
      }
    },
    {
      "type": {
        "label": ",",
        "beforeExpr": true,
        "startsExpr": false,
        "rightAssociative": false,
        "isLoop": false,
        "isAssign": false,
        "prefix": false,
        "postfix": false,
        "binop": null,
        "updateContext": null
      },
      "start": 355,
      "end": 356,
      "loc": {
        "start": {
          "line": 8,
          "column": 43
        },
        "end": {
          "line": 8,
          "column": 44
        }
      }
    },
    {
      "type": "CommentBlock",
      "value": "*\n   * @type {RemoteChromeWARCGenerator}\n   ",
      "start": 360,
      "end": 408,
      "loc": {
        "start": {
          "line": 10,
          "column": 2
        },
        "end": {
          "line": 12,
          "column": 5
        }
      }
    },
    {
      "type": {
        "label": "name",
        "beforeExpr": false,
        "startsExpr": true,
        "rightAssociative": false,
        "isLoop": false,
        "isAssign": false,
        "prefix": false,
        "postfix": false,
        "binop": null
      },
      "value": "RemoteChromeWARCWriter",
      "start": 411,
      "end": 433,
      "loc": {
        "start": {
          "line": 13,
          "column": 2
        },
        "end": {
          "line": 13,
          "column": 24
        }
      }
    },
    {
      "type": {
        "label": ":",
        "beforeExpr": true,
        "startsExpr": false,
        "rightAssociative": false,
        "isLoop": false,
        "isAssign": false,
        "prefix": false,
        "postfix": false,
        "binop": null,
        "updateContext": null
      },
      "start": 433,
      "end": 434,
      "loc": {
        "start": {
          "line": 13,
          "column": 24
        },
        "end": {
          "line": 13,
          "column": 25
        }
      }
    },
    {
      "type": {
        "label": "name",
        "beforeExpr": false,
        "startsExpr": true,
        "rightAssociative": false,
        "isLoop": false,
        "isAssign": false,
        "prefix": false,
        "postfix": false,
        "binop": null
      },
      "value": "require",
      "start": 435,
      "end": 442,
      "loc": {
        "start": {
          "line": 13,
          "column": 26
        },
        "end": {
          "line": 13,
          "column": 33
        }
      }
    },
    {
      "type": {
        "label": "(",
        "beforeExpr": true,
        "startsExpr": true,
        "rightAssociative": false,
        "isLoop": false,
        "isAssign": false,
        "prefix": false,
        "postfix": false,
        "binop": null
      },
      "start": 442,
      "end": 443,
      "loc": {
        "start": {
          "line": 13,
          "column": 33
        },
        "end": {
          "line": 13,
          "column": 34
        }
      }
    },
    {
      "type": {
        "label": "string",
        "beforeExpr": false,
        "startsExpr": true,
        "rightAssociative": false,
        "isLoop": false,
        "isAssign": false,
        "prefix": false,
        "postfix": false,
        "binop": null,
        "updateContext": null
      },
      "value": "./remoteChrome",
      "start": 443,
      "end": 459,
      "loc": {
        "start": {
          "line": 13,
          "column": 34
        },
        "end": {
          "line": 13,
          "column": 50
        }
      }
    },
    {
      "type": {
        "label": ")",
        "beforeExpr": false,
        "startsExpr": false,
        "rightAssociative": false,
        "isLoop": false,
        "isAssign": false,
        "prefix": false,
        "postfix": false,
        "binop": null
      },
      "start": 459,
      "end": 460,
      "loc": {
        "start": {
          "line": 13,
          "column": 50
        },
        "end": {
          "line": 13,
          "column": 51
        }
      }
    },
    {
      "type": {
        "label": ",",
        "beforeExpr": true,
        "startsExpr": false,
        "rightAssociative": false,
        "isLoop": false,
        "isAssign": false,
        "prefix": false,
        "postfix": false,
        "binop": null,
        "updateContext": null
      },
      "start": 460,
      "end": 461,
      "loc": {
        "start": {
          "line": 13,
          "column": 51
        },
        "end": {
          "line": 13,
          "column": 52
        }
      }
    },
    {
      "type": "CommentBlock",
      "value": "*\n   * @type {PuppeteerCDPWARCGenerator}\n   ",
      "start": 465,
      "end": 513,
      "loc": {
        "start": {
          "line": 15,
          "column": 2
        },
        "end": {
          "line": 17,
          "column": 5
        }
      }
    },
    {
      "type": {
        "label": "name",
        "beforeExpr": false,
        "startsExpr": true,
        "rightAssociative": false,
        "isLoop": false,
        "isAssign": false,
        "prefix": false,
        "postfix": false,
        "binop": null
      },
      "value": "PuppeteerCDPWARCGenerator",
      "start": 516,
      "end": 541,
      "loc": {
        "start": {
          "line": 18,
          "column": 2
        },
        "end": {
          "line": 18,
          "column": 27
        }
      }
    },
    {
      "type": {
        "label": ":",
        "beforeExpr": true,
        "startsExpr": false,
        "rightAssociative": false,
        "isLoop": false,
        "isAssign": false,
        "prefix": false,
        "postfix": false,
        "binop": null,
        "updateContext": null
      },
      "start": 541,
      "end": 542,
      "loc": {
        "start": {
          "line": 18,
          "column": 27
        },
        "end": {
          "line": 18,
          "column": 28
        }
      }
    },
    {
      "type": {
        "label": "name",
        "beforeExpr": false,
        "startsExpr": true,
        "rightAssociative": false,
        "isLoop": false,
        "isAssign": false,
        "prefix": false,
        "postfix": false,
        "binop": null
      },
      "value": "require",
      "start": 543,
      "end": 550,
      "loc": {
        "start": {
          "line": 18,
          "column": 29
        },
        "end": {
          "line": 18,
          "column": 36
        }
      }
    },
    {
      "type": {
        "label": "(",
        "beforeExpr": true,
        "startsExpr": true,
        "rightAssociative": false,
        "isLoop": false,
        "isAssign": false,
        "prefix": false,
        "postfix": false,
        "binop": null
      },
      "start": 550,
      "end": 551,
      "loc": {
        "start": {
          "line": 18,
          "column": 36
        },
        "end": {
          "line": 18,
          "column": 37
        }
      }
    },
    {
      "type": {
        "label": "string",
        "beforeExpr": false,
        "startsExpr": true,
        "rightAssociative": false,
        "isLoop": false,
        "isAssign": false,
        "prefix": false,
        "postfix": false,
        "binop": null,
        "updateContext": null
      },
      "value": "./puppeteerCDP",
      "start": 551,
      "end": 567,
      "loc": {
        "start": {
          "line": 18,
          "column": 37
        },
        "end": {
          "line": 18,
          "column": 53
        }
      }
    },
    {
      "type": {
        "label": ")",
        "beforeExpr": false,
        "startsExpr": false,
        "rightAssociative": false,
        "isLoop": false,
        "isAssign": false,
        "prefix": false,
        "postfix": false,
        "binop": null
      },
      "start": 567,
      "end": 568,
      "loc": {
        "start": {
          "line": 18,
          "column": 53
        },
        "end": {
          "line": 18,
          "column": 54
        }
      }
    },
    {
      "type": {
        "label": ",",
        "beforeExpr": true,
        "startsExpr": false,
        "rightAssociative": false,
        "isLoop": false,
        "isAssign": false,
        "prefix": false,
        "postfix": false,
        "binop": null,
        "updateContext": null
      },
      "start": 568,
      "end": 569,
      "loc": {
        "start": {
          "line": 18,
          "column": 54
        },
        "end": {
          "line": 18,
          "column": 55
        }
      }
    },
    {
      "type": "CommentBlock",
      "value": "*\n   * @type {PuppeteerWARCGenerator}\n   ",
      "start": 573,
      "end": 618,
      "loc": {
        "start": {
          "line": 20,
          "column": 2
        },
        "end": {
          "line": 22,
          "column": 5
        }
      }
    },
    {
      "type": {
        "label": "name",
        "beforeExpr": false,
        "startsExpr": true,
        "rightAssociative": false,
        "isLoop": false,
        "isAssign": false,
        "prefix": false,
        "postfix": false,
        "binop": null
      },
      "value": "PuppeteerWARCGenerator",
      "start": 621,
      "end": 643,
      "loc": {
        "start": {
          "line": 23,
          "column": 2
        },
        "end": {
          "line": 23,
          "column": 24
        }
      }
    },
    {
      "type": {
        "label": ":",
        "beforeExpr": true,
        "startsExpr": false,
        "rightAssociative": false,
        "isLoop": false,
        "isAssign": false,
        "prefix": false,
        "postfix": false,
        "binop": null,
        "updateContext": null
      },
      "start": 643,
      "end": 644,
      "loc": {
        "start": {
          "line": 23,
          "column": 24
        },
        "end": {
          "line": 23,
          "column": 25
        }
      }
    },
    {
      "type": {
        "label": "name",
        "beforeExpr": false,
        "startsExpr": true,
        "rightAssociative": false,
        "isLoop": false,
        "isAssign": false,
        "prefix": false,
        "postfix": false,
        "binop": null
      },
      "value": "require",
      "start": 645,
      "end": 652,
      "loc": {
        "start": {
          "line": 23,
          "column": 26
        },
        "end": {
          "line": 23,
          "column": 33
        }
      }
    },
    {
      "type": {
        "label": "(",
        "beforeExpr": true,
        "startsExpr": true,
        "rightAssociative": false,
        "isLoop": false,
        "isAssign": false,
        "prefix": false,
        "postfix": false,
        "binop": null
      },
      "start": 652,
      "end": 653,
      "loc": {
        "start": {
          "line": 23,
          "column": 33
        },
        "end": {
          "line": 23,
          "column": 34
        }
      }
    },
    {
      "type": {
        "label": "string",
        "beforeExpr": false,
        "startsExpr": true,
        "rightAssociative": false,
        "isLoop": false,
        "isAssign": false,
        "prefix": false,
        "postfix": false,
        "binop": null,
        "updateContext": null
      },
      "value": "./puppeteer",
      "start": 653,
      "end": 666,
      "loc": {
        "start": {
          "line": 23,
          "column": 34
        },
        "end": {
          "line": 23,
          "column": 47
        }
      }
    },
    {
      "type": {
        "label": ")",
        "beforeExpr": false,
        "startsExpr": false,
        "rightAssociative": false,
        "isLoop": false,
        "isAssign": false,
        "prefix": false,
        "postfix": false,
        "binop": null
      },
      "start": 666,
      "end": 667,
      "loc": {
        "start": {
          "line": 23,
          "column": 47
        },
        "end": {
          "line": 23,
          "column": 48
        }
      }
    },
    {
      "type": {
        "label": ",",
        "beforeExpr": true,
        "startsExpr": false,
        "rightAssociative": false,
        "isLoop": false,
        "isAssign": false,
        "prefix": false,
        "postfix": false,
        "binop": null,
        "updateContext": null
      },
      "start": 667,
      "end": 668,
      "loc": {
        "start": {
          "line": 23,
          "column": 48
        },
        "end": {
          "line": 23,
          "column": 49
        }
      }
    },
    {
      "type": "CommentBlock",
      "value": "*\n   * @type {WARCWriterBase}\n   ",
      "start": 672,
      "end": 709,
      "loc": {
        "start": {
          "line": 25,
          "column": 2
        },
        "end": {
          "line": 27,
          "column": 5
        }
      }
    },
    {
      "type": {
        "label": "name",
        "beforeExpr": false,
        "startsExpr": true,
        "rightAssociative": false,
        "isLoop": false,
        "isAssign": false,
        "prefix": false,
        "postfix": false,
        "binop": null
      },
      "value": "WARCWriterBase",
      "start": 712,
      "end": 726,
      "loc": {
        "start": {
          "line": 28,
          "column": 2
        },
        "end": {
          "line": 28,
          "column": 16
        }
      }
    },
    {
      "type": {
        "label": ":",
        "beforeExpr": true,
        "startsExpr": false,
        "rightAssociative": false,
        "isLoop": false,
        "isAssign": false,
        "prefix": false,
        "postfix": false,
        "binop": null,
        "updateContext": null
      },
      "start": 726,
      "end": 727,
      "loc": {
        "start": {
          "line": 28,
          "column": 16
        },
        "end": {
          "line": 28,
          "column": 17
        }
      }
    },
    {
      "type": {
        "label": "name",
        "beforeExpr": false,
        "startsExpr": true,
        "rightAssociative": false,
        "isLoop": false,
        "isAssign": false,
        "prefix": false,
        "postfix": false,
        "binop": null
      },
      "value": "require",
      "start": 728,
      "end": 735,
      "loc": {
        "start": {
          "line": 28,
          "column": 18
        },
        "end": {
          "line": 28,
          "column": 25
        }
      }
    },
    {
      "type": {
        "label": "(",
        "beforeExpr": true,
        "startsExpr": true,
        "rightAssociative": false,
        "isLoop": false,
        "isAssign": false,
        "prefix": false,
        "postfix": false,
        "binop": null
      },
      "start": 735,
      "end": 736,
      "loc": {
        "start": {
          "line": 28,
          "column": 25
        },
        "end": {
          "line": 28,
          "column": 26
        }
      }
    },
    {
      "type": {
        "label": "string",
        "beforeExpr": false,
        "startsExpr": true,
        "rightAssociative": false,
        "isLoop": false,
        "isAssign": false,
        "prefix": false,
        "postfix": false,
        "binop": null,
        "updateContext": null
      },
      "value": "./warcWriterBase",
      "start": 736,
      "end": 754,
      "loc": {
        "start": {
          "line": 28,
          "column": 26
        },
        "end": {
          "line": 28,
          "column": 44
        }
      }
    },
    {
      "type": {
        "label": ")",
        "beforeExpr": false,
        "startsExpr": false,
        "rightAssociative": false,
        "isLoop": false,
        "isAssign": false,
        "prefix": false,
        "postfix": false,
        "binop": null
      },
      "start": 754,
      "end": 755,
      "loc": {
        "start": {
          "line": 28,
          "column": 44
        },
        "end": {
          "line": 28,
          "column": 45
        }
      }
    },
    {
      "type": {
        "label": "}",
        "beforeExpr": false,
        "startsExpr": false,
        "rightAssociative": false,
        "isLoop": false,
        "isAssign": false,
        "prefix": false,
        "postfix": false,
        "binop": null
      },
      "start": 756,
      "end": 757,
      "loc": {
        "start": {
          "line": 29,
          "column": 0
        },
        "end": {
          "line": 29,
          "column": 1
        }
      }
    },
    {
      "type": {
        "label": "eof",
        "beforeExpr": false,
        "startsExpr": false,
        "rightAssociative": false,
        "isLoop": false,
        "isAssign": false,
        "prefix": false,
        "postfix": false,
        "binop": null,
        "updateContext": null
      },
      "start": 758,
      "end": 758,
      "loc": {
        "start": {
          "line": 30,
          "column": 0
        },
        "end": {
          "line": 30,
          "column": 0
        }
      }
    }
  ]
}